[
  {
    "img": "img-pm/kp41.png",
    "title": "万豪精品油画收藏鉴赏专场",
    "em": "万豪艺术品",
    "span": "5504",
    "img1": "img-pm/kp42.png",
    "em1": "1",
    "img2": "img-pm/kp43.png",
    "em2": "1,500",
    "img3": "img-pm/kp44.png",
    "em3": "600"
  },
  {
    "img": "img-pm/kp.jpg",
    "title": "环球名表钜惠捡漏专场",
    "em": "易掌奢侈品",
    "span": "95",
    "img1": "img-pm/kp2.jpg",
    "em1": "6,800",
    "img2": "img-pm/kp3.jpg",
    "em2": "8,500",
    "img3": "img-pm/kp4.jpg",
    "em3": "5,000"
  },
  {
    "img": "img-pm/kp5.png",
    "title": "珺珑玉器和田玉收藏保值专场",
    "em": "贵凯珠宝",
    "span": "20",
    "img1": "img-pm/kp6.png",
    "em1": "188",
    "img2": "img-pm/kp7.png",
    "em2": "188",
    "img3": "img-pm/kp8.png",
    "em3": "188"
  },
  {
    "img": "img-pm/kp9.jpg",
    "title": "金嘉玉源选臻品翡翠拍卖专场",
    "em": "金嘉玉源珠宝",
    "span": "573",
    "img1": "img-pm/kp10.jpg",
    "em1": "5,000",
    "img2": "img-pm/kp11.jpg",
    "em2": "3,500",
    "img3": "img-pm/kp12.jpg",
    "em3": "1,400"
  },
  {
    "img": "img-pm/kp13.png",
    "title": "源头翡翠拍卖瑞俪珠宝专场",
    "em": "瑞俪珠宝",
    "span": "530",
    "img1": "img-pm/kp14.png",
    "em1": "1,600",
    "img2": "img-pm/kp15.png",
    "em2": "500",
    "img3": "img-pm/kp16.png",
    "em3": "1,500"
  },
  {
    "img": "img-pm/kp17.png",
    "title": "蹉跎岁月似水流年-钱币邮票",
    "em": "红藏汇",
    "span": "372",
    "img1": "img-pm/kp18.png",
    "em1": "120",
    "img2": "img-pm/kp19.png",
    "em2": "155",
    "img3": "img-pm/kp20.png",
    "em3": "155"
  },
  {
    "img": "img-pm/kp21.png",
    "title": "蹉跎岁月似水流年-老照片",
    "em": "红藏汇",
    "span": "1161",
    "img1": "img-pm/kp22.png",
    "em1": "29",
    "img2": "img-pm/kp23.png",
    "em2": "600",
    "img3": "img-pm/kp24.png",
    "em3": "21"
  },
  {
    "img": "img-pm/kp25.png",
    "title": "钧瓷大师臻品收藏捡漏专场",
    "em": "华夏一佳",
    "span": "357",
    "img1": "img-pm/kp26.png",
    "em1": "331",
    "img2": "img-pm/kp27.png",
    "em2": "131",
    "img3": "img-pm/kp28.png",
    "em3": "799"
  },
  {
    "img": "img-pm/kp29.png",
    "title": "石时代臻品和田玉保值专场",
    "em": "石时代珠宝玉器",
    "span": "1141",
    "img1": "img-pm/kp30.png",
    "em1": "401",
    "img2": "img-pm/kp31.png",
    "em2": "388",
    "img3": "img-pm/kp32.png",
    "em3": "1,588"
  },
  {
    "img": "img-pm/kp33.png",
    "title": "万年猛犸牙雕捡漏专场",
    "em": "景荣文玩",
    "span": "27",
    "img1": "img-pm/kp34.png",
    "em1": "2,300",
    "img2": "img-pm/kp35.png",
    "em2": "2,000",
    "img3": "img-pm/kp36.png",
    "em3": "800"
  },
  {
    "img": "img-pm/kp37.png",
    "title": "产地直供臻品紫砂钜惠专场",
    "em": "产地直供臻品紫砂钜惠专场",
    "span": "42",
    "img1": "img-pm/kp38.png",
    "em1": "800",
    "img2": "img-pm/kp39.png",
    "em2": "800",
    "img3": "img-pm/kp40.png",
    "em3": "500"
  },
  {
    "img": "img-pm/kp45.png",
    "title": "经典皇家银器专场",
    "em": "易拍全球",
    "span": "0",
    "img1": "img-pm/kp46.png",
    "em1": "8,800",
    "img2": "img-pm/kp47.png",
    "em2": "7,600",
    "img3": "img-pm/kp48.png",
    "em3": "8,300"
  }
]
